jupyter_shiny_proxy/__init__.py
jupyter_shiny_proxy/icons/shiny.svg
jupyter_shiny_proxy-1.3.dist-info/LICENSE
jupyter_shiny_proxy-1.3.dist-info/METADATA
jupyter_shiny_proxy-1.3.dist-info/WHEEL
jupyter_shiny_proxy-1.3.dist-info/entry_points.txt
jupyter_shiny_proxy-1.3.dist-info/top_level.txt
jupyter_shiny_proxy-1.3.dist-info/RECORD
